setup.cfg
setup.py
nfg/__init__.py
nfg.mt940.egg-info/PKG-INFO
nfg.mt940.egg-info/SOURCES.txt
nfg.mt940.egg-info/dependency_links.txt
nfg.mt940.egg-info/entry_points.txt
nfg.mt940.egg-info/not-zip-safe
nfg.mt940.egg-info/top_level.txt
nfg/mt940/__init__.py
nfg/mt940/parser.py
nfg/mt940/tests.py