Metadata-Version: 1.0
Name: nfg.mt940
Version: 0.2dev
Summary: Parser for MT940 files
Home-page: http://www.nfg.nl
Author: NFG Net Facilities Group BV
Author-email: support@nfg.nl
License: GPLv3
Keywords: swift mt940 banking
Platform: UNKNOWN
